pytest_rich_reporter/__init__.py
pytest_rich_reporter/console.py
pytest_rich_reporter/plugin.py
pytest_rich_reporter/reporter.py
pytest_rich_reporter-0.0.1a0.dist-info/LICENSE
pytest_rich_reporter-0.0.1a0.dist-info/METADATA
pytest_rich_reporter-0.0.1a0.dist-info/WHEEL
pytest_rich_reporter-0.0.1a0.dist-info/entry_points.txt
pytest_rich_reporter-0.0.1a0.dist-info/top_level.txt
pytest_rich_reporter-0.0.1a0.dist-info/RECORD
