Metadata-Version: 2.1
Name: pytest-rich-reporter
Version: 0.0.1a0
Summary: A pytest plugin using Rich for beautiful test result formatting.
Home-page: https://github.com/joshuadavidthomas/pytest-rich-reporter
Author: Josh Thomas
Author-email: josh@joshthomas.dev
Maintainer: Josh Thomas
Maintainer-email: josh@joshthomas.dev
License: MIT
Project-URL: Bug Tracker, https://github.com/joshuadavidthomas/pytest-rich-reporter/issues
Platform: UNKNOWN
Classifier: Development Status :: 1 - Planning
Classifier: Environment :: Console
Classifier: Framework :: Pytest
Classifier: Intended Audience :: Developers
Classifier: License :: OSI Approved :: MIT License
Classifier: Operating System :: OS Independent
Classifier: Programming Language :: Python
Classifier: Programming Language :: Python :: 3
Classifier: Programming Language :: Python :: 3.7
Classifier: Programming Language :: Python :: 3.8
Classifier: Programming Language :: Python :: 3.9
Classifier: Programming Language :: Python :: 3.10
Classifier: Programming Language :: Python :: 3 :: Only
Classifier: Programming Language :: Python :: Implementation :: CPython
Classifier: Topic :: Software Development :: Testing
Requires-Python: >=3.7
License-File: LICENSE
Requires-Dist: pytest (>=5.0.0)
Requires-Dist: rich
